yubin_mcp/__init__.py
yubin_mcp/server.py
yubin_mcp-0.0.6.dist-info/licenses/LICENSE
yubin_mcp-0.0.6.dist-info/METADATA
yubin_mcp-0.0.6.dist-info/WHEEL
yubin_mcp-0.0.6.dist-info/entry_points.txt
yubin_mcp-0.0.6.dist-info/top_level.txt
yubin_mcp-0.0.6.dist-info/RECORD
